mapflow/__init__.py
mapflow/_classic.py
mapflow/_misc.py
mapflow/_quiver.py
mapflow/_static/world.gpkg
mapflow-0.2.14.dist-info/METADATA
mapflow-0.2.14.dist-info/WHEEL
mapflow-0.2.14.dist-info/licenses/LICENSE
mapflow-0.2.14.dist-info/RECORD
