Metadata-Version: 2.4
Name: mapflow
Version: 0.2.14
Summary: A Python library to export xarray.DataArray as video files
Project-URL: Homepage, https://github.com/CyrilJl/mapflow
Project-URL: Documentation, https://mapflow.readthedocs.io
Author: Cyril Joly
License: MIT
License-File: LICENSE
Requires-Python: >=3.10
Requires-Dist: geopandas
Requires-Dist: matplotlib
Requires-Dist: tqdm
Requires-Dist: xarray
